classic/migrations/__init__.py
classic/migrations/__main__.py
classic/migrations/connections.py
classic/migrations/exceptions.py
classic/migrations/migrations.py
classic/migrations/settings.py
classic/migrations/topologicalsort.py
classic/migrations/utils.py
classic/migrations/backends/__init__.py
classic/migrations/backends/base.py
classic/migrations/backends/contrib/__init__.py
classic/migrations/backends/contrib/odbc.py
classic/migrations/backends/contrib/oracle.py
classic/migrations/backends/contrib/pymssql.py
classic/migrations/backends/contrib/redshift.py
classic/migrations/backends/contrib/snowflake.py
classic/migrations/backends/core/__init__.py
classic/migrations/backends/core/mysql.py
classic/migrations/backends/core/postgresql.py
classic/migrations/backends/core/sqlite3.py
classic/migrations/scripts/__init__.py
classic/migrations/scripts/init.py
classic/migrations/scripts/main.py
classic/migrations/scripts/migrate.py
classic/migrations/scripts/newmigration.py
classic_migrations-0.0.16.dist-info/licenses/LICENSE.txt
classic_migrations-0.0.16.dist-info/METADATA
classic_migrations-0.0.16.dist-info/WHEEL
classic_migrations-0.0.16.dist-info/entry_points.txt
classic_migrations-0.0.16.dist-info/top_level.txt
classic_migrations-0.0.16.dist-info/RECORD
