Metadata-Version: 2.4
Name: classic-migrations
Version: 0.0.16
Summary: Database migrations with SQL
Home-page: https://github.com/variasov/classic-migrations
Author: Kazakovtsev Nikolay
Author-email: acidos@yandex.ru
License: Apache-2.0
Keywords: migrations migrate database alembic south
Classifier: Development Status :: 5 - Production/Stable
Classifier: Environment :: Console
Classifier: Intended Audience :: Developers
Classifier: Operating System :: OS Independent
Classifier: Topic :: Database
Classifier: Topic :: Database :: Front-Ends
Classifier: Topic :: Software Development
Classifier: Topic :: Software Development :: Version Control
Classifier: Programming Language :: Python :: 3
Requires-Python: >=3.10
License-File: LICENSE.txt
Requires-Dist: sqlparse
Requires-Dist: tabulate
Requires-Dist: importlib_metadata>=3.6.0
Requires-Dist: pydantic-settings~=2.6
Requires-Dist: pydantic~=2.11
Requires-Dist: setuptools~=78.1.0
Provides-Extra: mysql
Requires-Dist: PyMySQL; extra == "mysql"
Provides-Extra: postgres
Requires-Dist: psycopg2-binary==2.9.9; extra == "postgres"
Provides-Extra: pyodbc
Requires-Dist: pyodbc; extra == "pyodbc"
Provides-Extra: pymssql
Requires-Dist: pymssql==2.3.1; extra == "pymssql"
Dynamic: author
Dynamic: author-email
Dynamic: classifier
Dynamic: description
Dynamic: description-content-type
Dynamic: home-page
Dynamic: keywords
Dynamic: license
Dynamic: license-file
Dynamic: provides-extra
Dynamic: requires-dist
Dynamic: requires-python
Dynamic: summary
